{
	"id": 0,
	"name": "@sugoi/socket",
	"kind": 0,
	"flags": {},
	"children": [
		{
			"id": 1,
			"name": "CONNECTION_STATUS",
			"kind": 4,
			"kindString": "Enumeration",
			"flags": {
				"isExported": true
			},
			"children": [
				{
					"id": 2,
					"name": "CONNECTED",
					"kind": 16,
					"kindString": "Enumeration member",
					"flags": {
						"isExported": true
					},
					"sources": [
						{
							"fileName": "constants/connection-status.constant.ts",
							"line": 2,
							"character": 15
						}
					],
					"defaultValue": "\"CONNECTED\""
				},
				{
					"id": 3,
					"name": "DISCONNECTED",
					"kind": 16,
					"kindString": "Enumeration member",
					"flags": {
						"isExported": true
					},
					"sources": [
						{
							"fileName": "constants/connection-status.constant.ts",
							"line": 3,
							"character": 18
						}
					],
					"defaultValue": "\"DISCONNECTED\""
				}
			],
			"groups": [
				{
					"title": "Enumeration members",
					"kind": 16,
					"children": [
						2,
						3
					]
				}
			],
			"sources": [
				{
					"fileName": "constants/connection-status.constant.ts",
					"line": 1,
					"character": 29
				}
			]
		},
		{
			"id": 38,
			"name": "SocketError",
			"kind": 128,
			"kindString": "Class",
			"flags": {
				"isExported": true
			},
			"children": [
				{
					"id": 39,
					"name": "constructor",
					"kind": 512,
					"kindString": "Constructor",
					"flags": {
						"isExported": true
					},
					"signatures": [
						{
							"id": 40,
							"name": "new SocketError",
							"kind": 16384,
							"kindString": "Constructor signature",
							"flags": {},
							"parameters": [
								{
									"id": 41,
									"name": "message",
									"kind": 32768,
									"kindString": "Parameter",
									"flags": {},
									"type": {
										"type": "intrinsic",
										"name": "any"
									}
								},
								{
									"id": 42,
									"name": "code",
									"kind": 32768,
									"kindString": "Parameter",
									"flags": {},
									"type": {
										"type": "intrinsic",
										"name": "any"
									}
								}
							],
							"type": {
								"type": "reference",
								"name": "SocketError",
								"id": 38
							},
							"overwrites": {
								"type": "reference",
								"name": "SugoiError.__constructor"
							}
						}
					],
					"sources": [
						{
							"fileName": "exceptions/socket.exception.ts",
							"line": 3,
							"character": 45
						}
					],
					"overwrites": {
						"type": "reference",
						"name": "SugoiError.__constructor"
					}
				},
				{
					"id": 43,
					"name": "code",
					"kind": 1024,
					"kindString": "Property",
					"flags": {
						"isExported": true
					},
					"sources": [
						{
							"fileName": "node_modules/@sugoi/core/dist/exceptions/sugoi-abstract.exception.d.ts",
							"line": 2,
							"character": 8
						}
					],
					"type": {
						"type": "intrinsic",
						"name": "number"
					},
					"inheritedFrom": {
						"type": "reference",
						"name": "SugoiError.code"
					}
				},
				{
					"id": 44,
					"name": "message",
					"kind": 1024,
					"kindString": "Property",
					"flags": {
						"isExported": true
					},
					"sources": [
						{
							"fileName": "node_modules/@sugoi/core/dist/exceptions/sugoi-abstract.exception.d.ts",
							"line": 3,
							"character": 11
						}
					],
					"type": {
						"type": "intrinsic",
						"name": "string"
					},
					"inheritedFrom": {
						"type": "reference",
						"name": "SugoiError.message"
					}
				},
				{
					"id": 45,
					"name": "stack",
					"kind": 1024,
					"kindString": "Property",
					"flags": {
						"isExported": true
					},
					"sources": [
						{
							"fileName": "node_modules/@sugoi/core/dist/exceptions/sugoi-abstract.exception.d.ts",
							"line": 4,
							"character": 9
						}
					],
					"type": {
						"type": "intrinsic",
						"name": "string"
					},
					"inheritedFrom": {
						"type": "reference",
						"name": "SugoiError.stack"
					}
				},
				{
					"id": 48,
					"name": "getCode",
					"kind": 2048,
					"kindString": "Method",
					"flags": {
						"isExported": true
					},
					"signatures": [
						{
							"id": 49,
							"name": "getCode",
							"kind": 4096,
							"kindString": "Call signature",
							"flags": {},
							"type": {
								"type": "intrinsic",
								"name": "number"
							},
							"inheritedFrom": {
								"type": "reference",
								"name": "SugoiError.getCode"
							}
						}
					],
					"sources": [
						{
							"fileName": "node_modules/@sugoi/core/dist/exceptions/sugoi-abstract.exception.d.ts",
							"line": 8,
							"character": 11
						}
					],
					"inheritedFrom": {
						"type": "reference",
						"name": "SugoiError.getCode"
					}
				},
				{
					"id": 46,
					"name": "getMessage",
					"kind": 2048,
					"kindString": "Method",
					"flags": {
						"isExported": true
					},
					"signatures": [
						{
							"id": 47,
							"name": "getMessage",
							"kind": 4096,
							"kindString": "Call signature",
							"flags": {},
							"type": {
								"type": "intrinsic",
								"name": "string"
							},
							"inheritedFrom": {
								"type": "reference",
								"name": "SugoiError.getMessage"
							}
						}
					],
					"sources": [
						{
							"fileName": "node_modules/@sugoi/core/dist/exceptions/sugoi-abstract.exception.d.ts",
							"line": 7,
							"character": 14
						}
					],
					"inheritedFrom": {
						"type": "reference",
						"name": "SugoiError.getMessage"
					}
				},
				{
					"id": 50,
					"name": "getStack",
					"kind": 2048,
					"kindString": "Method",
					"flags": {
						"isExported": true
					},
					"signatures": [
						{
							"id": 51,
							"name": "getStack",
							"kind": 4096,
							"kindString": "Call signature",
							"flags": {},
							"type": {
								"type": "intrinsic",
								"name": "string"
							},
							"inheritedFrom": {
								"type": "reference",
								"name": "SugoiError.getStack"
							}
						}
					],
					"sources": [
						{
							"fileName": "node_modules/@sugoi/core/dist/exceptions/sugoi-abstract.exception.d.ts",
							"line": 9,
							"character": 12
						}
					],
					"inheritedFrom": {
						"type": "reference",
						"name": "SugoiError.getStack"
					}
				},
				{
					"id": 54,
					"name": "printError",
					"kind": 2048,
					"kindString": "Method",
					"flags": {
						"isExported": true
					},
					"signatures": [
						{
							"id": 55,
							"name": "printError",
							"kind": 4096,
							"kindString": "Call signature",
							"flags": {},
							"type": {
								"type": "intrinsic",
								"name": "void"
							},
							"inheritedFrom": {
								"type": "reference",
								"name": "SugoiError.printError"
							}
						}
					],
					"sources": [
						{
							"fileName": "node_modules/@sugoi/core/dist/exceptions/sugoi-abstract.exception.d.ts",
							"line": 11,
							"character": 14
						}
					],
					"inheritedFrom": {
						"type": "reference",
						"name": "SugoiError.printError"
					}
				},
				{
					"id": 52,
					"name": "printStack",
					"kind": 2048,
					"kindString": "Method",
					"flags": {
						"isExported": true
					},
					"signatures": [
						{
							"id": 53,
							"name": "printStack",
							"kind": 4096,
							"kindString": "Call signature",
							"flags": {},
							"type": {
								"type": "intrinsic",
								"name": "void"
							},
							"inheritedFrom": {
								"type": "reference",
								"name": "SugoiError.printStack"
							}
						}
					],
					"sources": [
						{
							"fileName": "node_modules/@sugoi/core/dist/exceptions/sugoi-abstract.exception.d.ts",
							"line": 10,
							"character": 14
						}
					],
					"inheritedFrom": {
						"type": "reference",
						"name": "SugoiError.printStack"
					}
				}
			],
			"groups": [
				{
					"title": "Constructors",
					"kind": 512,
					"children": [
						39
					]
				},
				{
					"title": "Properties",
					"kind": 1024,
					"children": [
						43,
						44,
						45
					]
				},
				{
					"title": "Methods",
					"kind": 2048,
					"children": [
						48,
						46,
						50,
						54,
						52
					]
				}
			],
			"sources": [
				{
					"fileName": "exceptions/socket.exception.ts",
					"line": 3,
					"character": 24
				}
			],
			"extendedTypes": [
				{
					"type": "reference",
					"name": "SugoiError"
				}
			]
		},
		{
			"id": 4,
			"name": "socketService",
			"kind": 128,
			"kindString": "Class",
			"flags": {
				"isExported": true,
				"isAbstract": true
			},
			"decorators": [
				{
					"name": "Injectable",
					"type": {
						"type": "reference",
						"name": "Injectable"
					},
					"arguments": {}
				}
			],
			"children": [
				{
					"id": 22,
					"name": "addHandler",
					"kind": 2048,
					"kindString": "Method",
					"flags": {
						"isStatic": true,
						"isExported": true,
						"isPublic": true
					},
					"signatures": [
						{
							"id": 23,
							"name": "addHandler",
							"kind": 4096,
							"kindString": "Call signature",
							"flags": {},
							"parameters": [
								{
									"id": 24,
									"name": "event",
									"kind": 32768,
									"kindString": "Parameter",
									"flags": {},
									"type": {
										"type": "intrinsic",
										"name": "string"
									}
								},
								{
									"id": 25,
									"name": "callback",
									"kind": 32768,
									"kindString": "Parameter",
									"flags": {},
									"type": {
										"type": "reflection",
										"declaration": {
											"id": 26,
											"name": "__type",
											"kind": 65536,
											"kindString": "Type literal",
											"flags": {},
											"signatures": [
												{
													"id": 27,
													"name": "__call",
													"kind": 4096,
													"kindString": "Call signature",
													"flags": {},
													"parameters": [
														{
															"id": 28,
															"name": "args",
															"kind": 32768,
															"kindString": "Parameter",
															"flags": {
																"isRest": true
															},
															"type": {
																"type": "array",
																"elementType": {
																	"type": "intrinsic",
																	"name": "any"
																}
															}
														}
													],
													"type": {
														"type": "intrinsic",
														"name": "void"
													}
												}
											],
											"sources": [
												{
													"fileName": "services/socket.service.ts",
													"line": 45,
													"character": 53
												}
											]
										}
									}
								},
								{
									"id": 29,
									"name": "namespace",
									"kind": 32768,
									"kindString": "Parameter",
									"flags": {},
									"type": {
										"type": "intrinsic",
										"name": "string"
									},
									"defaultValue": "\"/\""
								}
							],
							"type": {
								"type": "intrinsic",
								"name": "void"
							}
						}
					],
					"sources": [
						{
							"fileName": "services/socket.service.ts",
							"line": 45,
							"character": 28
						}
					]
				},
				{
					"id": 5,
					"name": "getSocketServerByNamespace",
					"kind": 2048,
					"kindString": "Method",
					"flags": {
						"isStatic": true,
						"isExported": true,
						"isPublic": true
					},
					"signatures": [
						{
							"id": 6,
							"name": "getSocketServerByNamespace",
							"kind": 4096,
							"kindString": "Call signature",
							"flags": {},
							"parameters": [
								{
									"id": 7,
									"name": "namespace",
									"kind": 32768,
									"kindString": "Parameter",
									"flags": {},
									"type": {
										"type": "intrinsic",
										"name": "string"
									}
								}
							],
							"type": {
								"type": "reference",
								"name": "SocketIOStatic.Server"
							}
						}
					],
					"sources": [
						{
							"fileName": "services/socket.service.ts",
							"line": 15,
							"character": 44
						}
					]
				},
				{
					"id": 8,
					"name": "init",
					"kind": 2048,
					"kindString": "Method",
					"flags": {
						"isStatic": true,
						"isExported": true,
						"isPublic": true
					},
					"signatures": [
						{
							"id": 9,
							"name": "init",
							"kind": 4096,
							"kindString": "Call signature",
							"flags": {},
							"parameters": [
								{
									"id": 10,
									"name": "HttpServer",
									"kind": 32768,
									"kindString": "Parameter",
									"flags": {},
									"type": {
										"type": "intrinsic",
										"name": "any"
									}
								},
								{
									"id": 11,
									"name": "namespace",
									"kind": 32768,
									"kindString": "Parameter",
									"flags": {},
									"type": {
										"type": "intrinsic",
										"name": "string"
									},
									"defaultValue": "\"/\""
								},
								{
									"id": 12,
									"name": "socketConfig",
									"kind": 32768,
									"kindString": "Parameter",
									"flags": {},
									"type": {
										"type": "reflection",
										"declaration": {
											"id": 13,
											"name": "__type",
											"kind": 65536,
											"kindString": "Type literal",
											"flags": {}
										}
									},
									"defaultValue": " {}"
								},
								{
									"id": 14,
									"name": "connectionCallback",
									"kind": 32768,
									"kindString": "Parameter",
									"flags": {},
									"type": {
										"type": "reflection",
										"declaration": {
											"id": 15,
											"name": "__type",
											"kind": 65536,
											"kindString": "Type literal",
											"flags": {},
											"signatures": [
												{
													"id": 16,
													"name": "__call",
													"kind": 4096,
													"kindString": "Call signature",
													"flags": {},
													"parameters": [
														{
															"id": 17,
															"name": "socket",
															"kind": 32768,
															"kindString": "Parameter",
															"flags": {
																"isOptional": true
															},
															"type": {
																"type": "reference",
																"name": "SocketIOStatic.Socket"
															}
														}
													],
													"type": {
														"type": "intrinsic",
														"name": "void"
													}
												}
											],
											"sources": [
												{
													"fileName": "services/socket.service.ts",
													"line": 28,
													"character": 42
												}
											]
										}
									},
									"defaultValue": " () => {\r\n                       }"
								},
								{
									"id": 18,
									"name": "disconnectCallback",
									"kind": 32768,
									"kindString": "Parameter",
									"flags": {},
									"type": {
										"type": "reflection",
										"declaration": {
											"id": 19,
											"name": "__type",
											"kind": 65536,
											"kindString": "Type literal",
											"flags": {},
											"signatures": [
												{
													"id": 20,
													"name": "__call",
													"kind": 4096,
													"kindString": "Call signature",
													"flags": {},
													"parameters": [
														{
															"id": 21,
															"name": "socket",
															"kind": 32768,
															"kindString": "Parameter",
															"flags": {
																"isOptional": true
															},
															"type": {
																"type": "reference",
																"name": "SocketIOStatic.Socket"
															}
														}
													],
													"type": {
														"type": "intrinsic",
														"name": "void"
													}
												}
											],
											"sources": [
												{
													"fileName": "services/socket.service.ts",
													"line": 30,
													"character": 42
												}
											]
										}
									},
									"defaultValue": " () => {\r\n                       }"
								}
							],
							"type": {
								"type": "reference",
								"name": "SocketIOStatic.Server"
							}
						}
					],
					"sources": [
						{
							"fileName": "services/socket.service.ts",
							"line": 25,
							"character": 22
						}
					]
				}
			],
			"groups": [
				{
					"title": "Methods",
					"kind": 2048,
					"children": [
						22,
						5,
						8
					]
				}
			],
			"sources": [
				{
					"fileName": "services/socket.service.ts",
					"line": 9,
					"character": 35
				}
			]
		},
		{
			"id": 34,
			"name": "ISocketHandler",
			"kind": 256,
			"kindString": "Interface",
			"flags": {
				"isExported": true
			},
			"children": [
				{
					"id": 36,
					"name": "events",
					"kind": 1024,
					"kindString": "Property",
					"flags": {
						"isExported": true
					},
					"sources": [
						{
							"fileName": "interfaces/socket-handler.interface.ts",
							"line": 6,
							"character": 10
						}
					],
					"type": {
						"type": "reference",
						"name": "Array",
						"typeArguments": [
							{
								"type": "reflection",
								"declaration": {
									"id": 37,
									"name": "__type",
									"kind": 65536,
									"kindString": "Type literal",
									"flags": {},
									"sources": [
										{
											"fileName": "interfaces/socket-handler.interface.ts",
											"line": 6,
											"character": 17
										}
									]
								}
							}
						]
					}
				},
				{
					"id": 35,
					"name": "socket",
					"kind": 1024,
					"kindString": "Property",
					"flags": {
						"isExported": true
					},
					"sources": [
						{
							"fileName": "interfaces/socket-handler.interface.ts",
							"line": 5,
							"character": 10
						}
					],
					"type": {
						"type": "reference",
						"name": "SocketIOStatic.Socket"
					}
				}
			],
			"groups": [
				{
					"title": "Properties",
					"kind": 1024,
					"children": [
						36,
						35
					]
				}
			],
			"sources": [
				{
					"fileName": "interfaces/socket-handler.interface.ts",
					"line": 4,
					"character": 31
				}
			]
		},
		{
			"id": 30,
			"name": "SocketOn",
			"kind": 64,
			"kindString": "Function",
			"flags": {
				"isExported": true
			},
			"signatures": [
				{
					"id": 31,
					"name": "SocketOn",
					"kind": 4096,
					"kindString": "Call signature",
					"flags": {},
					"comment": {
						"shortText": "Register event callback per namespace",
						"returns": "\n",
						"tags": [
							{
								"tag": "example",
								"text": "\n @SocketOn('log')\n logging(data,socket){\n     console.log(data);\n     socket.emit(\"logged\",data);\n }"
							}
						]
					},
					"parameters": [
						{
							"id": 32,
							"name": "event",
							"kind": 32768,
							"kindString": "Parameter",
							"flags": {},
							"comment": {},
							"type": {
								"type": "intrinsic",
								"name": "string"
							}
						},
						{
							"id": 33,
							"name": "namespace",
							"kind": 32768,
							"kindString": "Parameter",
							"flags": {},
							"comment": {},
							"type": {
								"type": "intrinsic",
								"name": "string"
							},
							"defaultValue": "\"/\""
						}
					],
					"type": {
						"type": "reference",
						"name": "(Anonymous function)"
					}
				}
			],
			"sources": [
				{
					"fileName": "decorators/socket.ts",
					"line": 15,
					"character": 24
				}
			]
		}
	],
	"groups": [
		{
			"title": "Enumerations",
			"kind": 4,
			"children": [
				1
			]
		},
		{
			"title": "Classes",
			"kind": 128,
			"children": [
				38,
				4
			]
		},
		{
			"title": "Interfaces",
			"kind": 256,
			"children": [
				34
			]
		},
		{
			"title": "Functions",
			"kind": 64,
			"children": [
				30
			]
		}
	]
}